arborize/__init__.py
arborize/_util.py
arborize/constraints.py
arborize/definitions.py
arborize/exceptions.py
arborize/parameter.py
arborize/schematic.py
arborize/synapse.py
arborize/builders/__init__.py
arborize/builders/_arbor.py
arborize/builders/_bluepyopt.py
arborize/builders/_neuron.py
arborize/schematics/__init__.py
arborize/schematics/_bsb.py
arborize/schematics/_file.py
arborize-7.2.1.dist-info/licenses/LICENSE
arborize-7.2.1.dist-info/WHEEL
arborize-7.2.1.dist-info/METADATA
arborize-7.2.1.dist-info/RECORD
