Metadata-Version: 2.4
Name: arborize
Version: 7.2.1
Summary: Write descriptions for NEURON cell models in an Arbor-like manner for both the Arbor and
Author-email: Robin De Schepper <robin@alexandria.sc>
Requires-Python: >=3.10,<4
Classifier: License :: OSI Approved :: GNU General Public License v3 or later (GPLv3+)
License-File: LICENSE
Requires-Dist: numpy~=1.21
Requires-Dist: errr~=1.2
Requires-Dist: morphio>=3.3.6,<4
Requires-Dist: bsb-core~=7.0
Requires-Dist: arbor~=0.10 ; extra == "arbor"
Requires-Dist: nmodl-glia[arbor]~=7.0 ; extra == "arbor"
Requires-Dist: bluepyopt~=1.14 ; extra == "bluepyopt"
Requires-Dist: dill>=0.3.8 ; extra == "bluepyopt"
Requires-Dist: nrn-patch~=7.0 ; extra == "neuron"
Requires-Dist: nmodl-glia[neuron]~=7.0 ; extra == "neuron"
Requires-Dist: mpi4py~=3.0 ; extra == "parallel"
Provides-Extra: arbor
Provides-Extra: bluepyopt
Provides-Extra: neuron
Provides-Extra: parallel
